pytest_session2file/__init__.py
pytest_session2file/pytest_session2file.py
pytest_session2file-0.1.11.dist-info/LICENSE.md
pytest_session2file-0.1.11.dist-info/METADATA
pytest_session2file-0.1.11.dist-info/WHEEL
pytest_session2file-0.1.11.dist-info/entry_points.txt
pytest_session2file-0.1.11.dist-info/top_level.txt
pytest_session2file-0.1.11.dist-info/RECORD
