Metadata-Version: 2.1
Name: pytest-session2file
Version: 0.1.11
Summary: pytest-session2file (aka: pytest-session_to_file for v0.1.0 - v0.1.2) is a py.test plugin for capturing and saving to file the stdout of py.test.
Home-page: https://github.com/BuhtigithuB/pytest_session2file
Author: Richard Vézina
Author-email: ml.richard.vezina@gmail.com
License: LGPLv3 (http://www.gnu.org/licenses/lgpl.html)
Keywords: py.test pytest plugin plugins
Platform: UNKNOWN
Classifier: Development Status :: 3 - Alpha
Classifier: Intended Audience :: Developers
Classifier: Topic :: Software Development :: Testing
Classifier: License :: OSI Approved :: GNU Lesser General Public License v3 (LGPLv3)
Classifier: Programming Language :: Python :: 2.7
Requires-Dist: pytest
